counter.v
module counter(clk,period,duty,state,en); //period y duty en ms
	
	input clk;
	input en;
	input [31:0] period;
	input [31:0] duty;
	output reg state;
	

reg [5:0] contusec = 0;
reg [14:0] contmsec = 0;

reg [4:0] periodf = 0;
reg [4:0] dutyf = 0;

always @(posedge clk) begin
	
	if(en == 1)begin
		if(contusec == 50) begin //Se cuantan 50 ciclos de clk que equivale a 1us (para clk de 50MHz)
			contusec = 0;
		
			if(contmsec >= period-1) begin // se cuaenta period ms
				contmsec = 0;
			end else begin
				contmsec = contmsec + 1;
			end
		
		end else begin
			contusec = contusec + 1;
		end
	end
	
end

always @(posedge clk) begin
	
	if(en == 1)begin
		if(contmsec <= duty-1)begin
			state = 1;
		end else begin
			state = 0;
		end
	end
	
end

/*
always @(posedge clk) begin

	if(en == 1)begin
		dutyf = duty;
		periodf = period;
	end
end
*/

endmodule

pwm.v
`timescale 1ms / 1ns

module pwm(clk,rst,rd,wr,din,adrs,dout,pwmo);
	
	input clk;
	input rst;
	input rd;
	input wr;
	input [31:00] din;
	input [6:0] adrs;
	output reg [31:00] dout;
	output [7:0] pwmo;
	
reg [31:00] dinf;

reg [31:00] period0;
reg [31:00] period1;
reg [31:00] period2;
reg [31:00] period3;
reg [31:00] period4;
reg [31:00] period5;
reg [31:00] period6;
reg [31:00] period7;

reg [31:00] duty0;
reg [31:00] duty1;
reg [31:00] duty2;
reg [31:00] duty3;
reg [31:00] duty4;
reg [31:00] duty5;
reg [31:00] duty6;
reg [31:00] duty7;

reg en0;
reg en1;
reg en2;
reg en3;
reg en4;
reg en5;
reg en6;
reg en7;

	
counter pwm0(.clk(clk), .period(period0), .duty(duty0), .state(pwmo[0]), .en(en0));
counter pwm1(.clk(clk), .period(period1), .duty(duty1), .state(pwmo[1]), .en(en1));
counter pwm2(.clk(clk), .period(period2), .duty(duty2), .state(pwmo[2]), .en(en2));
counter pwm3(.clk(clk), .period(period3), .duty(duty3), .state(pwmo[3]), .en(en3));
counter pwm4(.clk(clk), .period(period4), .duty(duty4), .state(pwmo[4]), .en(en4));
counter pwm5(.clk(clk), .period(period5), .duty(duty5), .state(pwmo[5]), .en(en5));
counter pwm6(.clk(clk), .period(period6), .duty(duty6), .state(pwmo[6]), .en(en6));
counter pwm7(.clk(clk), .period(period7), .duty(duty7), .state(pwmo[7]), .en(en7));

	
	always @(posedge clk) begin
	
		if(wr == 1) begin
			
			dinf = din;
			
			case(adrs)
				7'h00: en0 = dinf;
				7'h04: period0 = dinf;
				7'h08: duty0 = dinf;
				
				7'h0c: en1 = dinf;
				7'h10: period1 = dinf;
				7'h14: duty1 = dinf;
				
				7'h18: en2 = dinf;
				7'h1c: period2 = dinf;
				7'h20: duty2 = dinf;
				
				7'h24: en3 = dinf;
				7'h28: period3 = dinf;
				7'h2c: duty3 = dinf;
				
				7'h30: en4 = dinf;
				7'h34: period4 = dinf;
				7'h38: duty4 = dinf;
				
				7'h3c: en5 = dinf;
				7'h40: period5 = dinf;
				7'h44: duty5 = dinf;
				
				7'h48: en6 = dinf;
				7'h4c: period6 = dinf;
				7'h50: duty6 = dinf;
				
				7'h54: en7 = dinf;
				7'h58: period7 = dinf;
				7'h5c: duty7 = dinf;
				
			default
				dinf = din;
				
			endcase
		end
		
		if(rd == 1) begin
			
			case(adrs)
				6'h00: dout = en0;
				6'h04: dout = period0;
				6'h08: dout = duty0;
				
				6'h0c: dout = en1;
				6'h10: dout = period1;
				6'h14: dout = duty1;
				
				6'h18: dout = en2;
				6'h1c: dout = period2;
				6'h20: dout = duty2;
				
				6'h24: dout = en3;
				6'h28: dout = period3;
				6'h2c: dout = duty3;
				
				6'h30: dout = en4;
				6'h34: dout = period4;
				6'h38: dout = duty4;
				
				6'h3c: dout = en5;
				6'h40: dout = period5;
				6'h44: dout = duty5;
				
				6'h48: dout = en6;
				6'h4c: dout = period6;
				6'h50: dout = duty6;
				
				6'h54: dout = en7;
				6'h58: dout = period7;
				6'h5c: dout = duty7;
				
			default
				dinf = din;
				
			endcase
		end
		
	end


endmodule

pwm_TB.v
`timescale 1ns / 1ns

module pwm_TB;
	reg clk;
	reg rst;
	reg rd;
	reg wr;
	reg [31:0] din;
	reg [6:0] adrs;
	wire [31:0] dout;
	wire [7:0] pwmo;
	
	pwm uut( .clk(clk), .rst(rst), .rd(rd), .wr(wr), .din(din), .adrs(adrs), .dout(dout), .pwmo(pwmo));
	
parameter tck              = 20;       // clock period in ns
parameter uart_baud_rate   = 1152000;  // uart baud rate for simulation 

parameter clk_freq = 1000000000 / tck; // Frequenzy in HZ
	
/* Clocking device */
initial         clk <= 0;
always #(tck/2) clk <= ~clk;

	initial begin
		
		wr = 1;
		din = 2;
		adrs = 7'h08;
		#20;
		din = 20;
		adrs = 7'h04;
		#20;
		din = 1;
		adrs = 7'h00;
		#20;
		
		din = 4;
		adrs = 7'h14;
		#20;
		din = 20;
		adrs = 7'h10;
		#20;
		din = 1;
		adrs = 7'h0c;
		#20;
		
		din = 2;
		adrs = 7'h20;
		#20;
		din = 20;
		adrs = 7'h1c;
		#20;
		din = 1;
		adrs = 7'h18;
		#20;
		
		din = 2;
		adrs = 7'h44;
		#20;
		din = 20;
		adrs = 7'h40;
		#20;
		din = 1;
		adrs = 7'h3c;
		#20;
		
		din = 2;
		adrs = 7'h5c;
		#20;
		din = 20;
		adrs = 7'h58;
		#20;
		din = 1;
		adrs = 7'h54;
		#20;
		
		wr = 0;
		rd = 1;
		adrs = 7'h04;
		#20;
		adrs = 7'h18;
		#20;
		adrs = 7'h5c;
		#20;
		adrs = 7'h00;
		#20;
		adrs = 7'h0;
		
		
		
	end

	initial begin: TEST_CASE
		$dumpfile("pwm_TB.vcd");
		$dumpvars(-1,uut);
		#(tck*20000) $finish;
	end

endmodule

simulation/pwm_TB.vcd
$date
	Mon Mar  5 21:32:55 2018
$end
$version
	Icarus Verilog
$end
$timescale
	1ns
$end
$scope module pwm_TB $end
$scope module uut $end
$var wire 7 ! adrs [6:0] $end
$var wire 1 " clk $end
$var wire 32 # din [31:0] $end
$var wire 8 $ pwmo [7:0] $end
$var wire 1 % rd $end
$var wire 1 & rst $end
$var wire 1 ' wr $end
$var reg 32 ( dinf [31:0] $end
$var reg 32 ) dout [31:0] $end
$var reg 32 * duty0 [31:0] $end
$var reg 32 + duty1 [31:0] $end
$var reg 32 , duty2 [31:0] $end
$var reg 32 - duty3 [31:0] $end
$var reg 32 . duty4 [31:0] $end
$var reg 32 / duty5 [31:0] $end
$var reg 32 0 duty6 [31:0] $end
$var reg 32 1 duty7 [31:0] $end
$var reg 1 2 en0 $end
$var reg 1 3 en1 $end
$var reg 1 4 en2 $end
$var reg 1 5 en3 $end
$var reg 1 6 en4 $end
$var reg 1 7 en5 $end
$var reg 1 8 en6 $end
$var reg 1 9 en7 $end
$var reg 32 : period0 [31:0] $end
$var reg 32 ; period1 [31:0] $end
$var reg 32 < period2 [31:0] $end
$var reg 32 = period3 [31:0] $end
$var reg 32 > period4 [31:0] $end
$var reg 32 ? period5 [31:0] $end
$var reg 32 @ period6 [31:0] $end
$var reg 32 A period7 [31:0] $end
$scope module pwm0 $end
$var wire 1 " clk $end
$var wire 32 B duty [31:0] $end
$var wire 1 C en $end
$var wire 32 D period [31:0] $end
$var reg 15 E contmsec [14:0] $end
$var reg 6 F contusec [5:0] $end
$var reg 5 G dutyf [4:0] $end
$var reg 5 H periodf [4:0] $end
$var reg 1 I state $end
$upscope $end
$scope module pwm1 $end
$var wire 1 " clk $end
$var wire 32 J duty [31:0] $end
$var wire 1 K en $end
$var wire 32 L period [31:0] $end
$var reg 15 M contmsec [14:0] $end
$var reg 6 N contusec [5:0] $end
$var reg 5 O dutyf [4:0] $end
$var reg 5 P periodf [4:0] $end
$var reg 1 Q state $end
$upscope $end
$scope module pwm2 $end
$var wire 1 " clk $end
$var wire 32 R duty [31:0] $end
$var wire 1 S en $end
$var wire 32 T period [31:0] $end
$var reg 15 U contmsec [14:0] $end
$var reg 6 V contusec [5:0] $end
$var reg 5 W dutyf [4:0] $end
$var reg 5 X periodf [4:0] $end
$var reg 1 Y state $end
$upscope $end
$scope module pwm3 $end
$var wire 1 " clk $end
$var wire 32 Z duty [31:0] $end
$var wire 1 [ en $end
$var wire 32 \ period [31:0] $end
$var reg 15 ] contmsec [14:0] $end
$var reg 6 ^ contusec [5:0] $end
$var reg 5 _ dutyf [4:0] $end
$var reg 5 ` periodf [4:0] $end
$var reg 1 a state $end
$upscope $end
$scope module pwm4 $end
$var wire 1 " clk $end
$var wire 32 b duty [31:0] $end
$var wire 1 c en $end
$var wire 32 d period [31:0] $end
$var reg 15 e contmsec [14:0] $end
$var reg 6 f contusec [5:0] $end
$var reg 5 g dutyf [4:0] $end
$var reg 5 h periodf [4:0] $end
$var reg 1 i state $end
$upscope $end
$scope module pwm5 $end
$var wire 1 " clk $end
$var wire 32 j duty [31:0] $end
$var wire 1 k en $end
$var wire 32 l period [31:0] $end
$var reg 15 m contmsec [14:0] $end
$var reg 6 n contusec [5:0] $end
$var reg 5 o dutyf [4:0] $end
$var reg 5 p periodf [4:0] $end
$var reg 1 q state $end
$upscope $end
$scope module pwm6 $end
$var wire 1 " clk $end
$var wire 32 r duty [31:0] $end
$var wire 1 s en $end
$var wire 32 t period [31:0] $end
$var reg 15 u contmsec [14:0] $end
$var reg 6 v contusec [5:0] $end
$var reg 5 w dutyf [4:0] $end
$var reg 5 x periodf [4:0] $end
$var reg 1 y state $end
$upscope $end
$scope module pwm7 $end
$var wire 1 " clk $end
$var wire 32 z duty [31:0] $end
$var wire 1 { en $end
$var wire 32 | period [31:0] $end
$var reg 15 } contmsec [14:0] $end
$var reg 6 ~ contusec [5:0] $end
$var reg 5 !" dutyf [4:0] $end
$var reg 5 "" periodf [4:0] $end
$var reg 1 #" state $end
$upscope $end
$upscope $end
$upscope $end
$enddefinitions $end
#0
$dumpvars
x#"
b0 ""
b0 !"
b0 ~
b0 }
bx |
x{
bx z
xy
b0 x
b0 w
b0 v
b0 u
bx t
xs
bx r
xq
b0 p
b0 o
b0 n
b0 m
bx l
xk
bx j
xi
b0 h
b0 g
b0 f
b0 e
bx d
xc
bx b
xa
b0 `
b0 _
b0 ^
b0 ]
bx \
x[
bx Z
xY
b0 X
b0 W
b0 V
b0 U
bx T
xS
bx R
xQ
b0 P
b0 O
b0 N
b0 M
bx L
xK
bx J
xI
b0 H
b0 G
b0 F
b0 E
bx D
xC
bx B
bx A
bx @
bx ?
bx >
bx =
bx <
bx ;
bx :
x9
x8
x7
x6
x5
x4
x3
x2
bx 1
bx 0
bx /
bx .
bx -
bx ,
bx +
bx *
bx )
bx (
1'
x&
x%
bx $
b10 #
0"
b1000 !
$end
#10
b10 *
b10 B
b10 (
1"
#20
0"
b100 !
b10100 #
#30
b10100 :
b10100 D
b10100 (
1"
#40
0"
b0 !
b1 #
#50
b1 F
1I
bx1 $
12
1C
b1 (
1"
#60
0"
b10100 !
b100 #
#70
b100 +
b100 J
b100 (
b10 F
1"
#80
0"
b10000 !
b10100 #
#90
b11 F
b10100 ;
b10100 L
b10100 (
1"
#100
0"
b1100 !
b1 #
#110
13
1K
b1 (
b100 F
1"
#120
0"
b100000 !
b10 #
#130
b101 F
b1 N
1Q
bx11 $
b10 ,
b10 R
b10 (
1"
#140
0"
b11100 !
b10100 #
#150
b10100 <
b10100 T
b10100 (
b10 N
b110 F
1"
#160
0"
b11000 !
b1 #
#170
b111 F
b11 N
b1 V
1Y
bx111 $
14
1S
b1 (
1"
#180
0"
b1000100 !
b10 #
#190
b10 /
b10 j
b10 (
b10 V
b100 N
b1000 F
1"
#200
0"
b1000000 !
b10100 #
#210
b1001 F
b101 N
b11 V
b10100 ?
b10100 l
b10100 (
1"
#220
0"
b111100 !
b1 #
#230
17
1k
b1 (
b100 V
b110 N
b1010 F
1"
#240
0"
b1011100 !
b10 #
#250
b1011 F
b111 N
b101 V
b1 n
1q
bx1xx111 $
b10 1
b10 z
b10 (
1"
#260
0"
b1011000 !
b10100 #
#270
b10100 A
b10100 |
b10100 (
b10 n
b110 V
b1000 N
b1100 F
1"
#280
0"
b1010100 !
b1 #
#290
b1101 F
b1001 N
b111 V
b11 n
b1 ~
1#"
b1x1xx111 $
19
1{
b1 (
1"
#300
0"
b100 !
1%
0'
#310
b10100 )
b10 ~
b100 n
b1000 V
b1010 N
b1110 F
1"
#320
0"
b11000 !
#330
b1111 F
b1011 N
b1001 V
b101 n
b11 ~
b1 )
1"
#340
0"
b1011100 !
#350
b100 ~
b110 n
b1010 V
b1100 N
b10000 F
1"
#360
0"
b0 !
#370
b10001 F
b1101 N
b1011 V
b111 n
b101 ~
1"
#380
0"
#390
b110 ~
b1000 n
b1100 V
b1110 N
b10010 F
1"
#400
0"
#410
b10011 F
b1111 N
b1101 V
b1001 n
b111 ~
1"
#420
0"
#430
b1000 ~
b1010 n
b1110 V
b10000 N
b10100 F
1"
#440
0"
#450
b10101 F
b10001 N
b1111 V
b1011 n
b1001 ~
1"
#460
0"
#470
b1010 ~
b1100 n
b10000 V
b10010 N
b10110 F
1"
#480
0"
#490
b10111 F
b10011 N
b10001 V
b1101 n
b1011 ~
1"
#500
0"
#510
b1100 ~
b1110 n
b10010 V
b10100 N
b11000 F
1"
#520
0"
#530
b11001 F
b10101 N
b10011 V
b1111 n
b1101 ~
1"
#540
0"
#550
b1110 ~
b10000 n
b10100 V
b10110 N
b11010 F
1"
#560
0"
#570
b11011 F
b10111 N
b10101 V
b10001 n
b1111 ~
1"
#580
0"
#590
b10000 ~
b10010 n
b10110 V
b11000 N
b11100 F
1"
#600
0"
#610
b11101 F
b11001 N
b10111 V
b10011 n
b10001 ~
1"
#620
0"
#630
b10010 ~
b10100 n
b11000 V
b11010 N
b11110 F
1"
#640
0"
#650
b11111 F
b11011 N
b11001 V
b10101 n
b10011 ~
1"
#660
0"
#670
b10100 ~
b10110 n
b11010 V
b11100 N
b100000 F
1"
#680
0"
#690
b100001 F
b11101 N
b11011 V
b10111 n
b10101 ~
1"
#700
0"
#710
b10110 ~
b11000 n
b11100 V
b11110 N
b100010 F
1"
#720
0"
#730
b100011 F
b11111 N
b11101 V
b11001 n
b10111 ~
1"
#740
0"
#750
b11000 ~
b11010 n
b11110 V
b100000 N
b100100 F
1"
#760
0"
#770
b100101 F
b100001 N
b11111 V
b11011 n
b11001 ~
1"
#780
0"
#790
b11010 ~
b11100 n
b100000 V
b100010 N
b100110 F
1"
#800
0"
#810
b100111 F
b100011 N
b100001 V
b11101 n
b11011 ~
1"
#820
0"
#830
b11100 ~
b11110 n
b100010 V
b100100 N
b101000 F
1"
#840
0"
#850
b101001 F
b100101 N
b100011 V
b11111 n
b11101 ~
1"
#860
0"
#870
b11110 ~
b100000 n
b100100 V
b100110 N
b101010 F
1"
#880
0"
#890
b101011 F
b100111 N
b100101 V
b100001 n
b11111 ~
1"
#900
0"
#910
b100000 ~
b100010 n
b100110 V
b101000 N
b101100 F
1"
#920
0"
#930
b101101 F
b101001 N
b100111 V
b100011 n
b100001 ~
1"
#940
0"
#950
b100010 ~
b100100 n
b101000 V
b101010 N
b101110 F
1"
#960
0"
#970
b101111 F
b101011 N
b101001 V
b100101 n
b100011 ~
1"
#980
0"
#990
b100100 ~
b100110 n
b101010 V
b101100 N
b110000 F
1"
#1000
0"
#1010
b110001 F
b101101 N
b101011 V
b100111 n
b100101 ~
1"
#1020
0"
#1030
b100110 ~
b101000 n
b101100 V
b101110 N
b110010 F
1"
#1040
0"
#1050
b1 E
b0 F
b101111 N
b101101 V
b101001 n
b100111 ~
1"
#1060
0"
#1070
b101000 ~
b101010 n
b101110 V
b110000 N
b1 F
1"
#1080
0"
#1090
b10 F
b110001 N
b101111 V
b101011 n
b101001 ~
1"
#1100
0"
#1110
b101010 ~
b101100 n
b110000 V
b110010 N
b11 F
1"
#1120
0"
#1130
b100 F
b1 M
b0 N
b110001 V
b101101 n
b101011 ~
1"
#1140
0"
#1150
b101100 ~
b101110 n
b110010 V
b1 N
b101 F
1"
#1160
0"
#1170
b110 F
b10 N
b1 U
b0 V
b101111 n
b101101 ~
1"
#1180
0"
#1190
b101110 ~
b110000 n
b1 V
b11 N
b111 F
1"
#1200
0"
#1210
b1000 F
b100 N
b10 V
b110001 n
b101111 ~
1"
#1220
0"
#1230
b110000 ~
b110010 n
b11 V
b101 N
b1001 F
1"
#1240
0"
#1250
b1010 F
b110 N
b100 V
b1 m
b0 n
b110001 ~
1"
#1260
0"
#1270
b110010 ~
b1 n
b101 V
b111 N
b1011 F
1"
#1280
0"
#1290
b1100 F
b1000 N
b110 V
b10 n
b1 }
b0 ~
1"
#1300
0"
#1310
b1 ~
b11 n
b111 V
b1001 N
b1101 F
1"
#1320
0"
#1330
b1110 F
b1010 N
b1000 V
b100 n
b10 ~
1"
#1340
0"
#1350
b11 ~
b101 n
b1001 V
b1011 N
b1111 F
1"
#1360
0"
#1370
b10000 F
b1100 N
b1010 V
b110 n
b100 ~
1"
#1380
0"
#1390
b101 ~
b111 n
b1011 V
b1101 N
b10001 F
1"
#1400
0"
#1410
b10010 F
b1110 N
b1100 V
b1000 n
b110 ~
1"
#1420
0"
#1430
b111 ~
b1001 n
b1101 V
b1111 N
b10011 F
1"
#1440
0"
#1450
b10100 F
b10000 N
b1110 V
b1010 n
b1000 ~
1"
#1460
0"
#1470
b1001 ~
b1011 n
b1111 V
b10001 N
b10101 F
1"
#1480
0"
#1490
b10110 F
b10010 N
b10000 V
b1100 n
b1010 ~
1"
#1500
0"
#1510
b1011 ~
b1101 n
b10001 V
b10011 N
b10111 F
1"
#1520
0"
#1530
b11000 F
b10100 N
b10010 V
b1110 n
b1100 ~
1"
#1540
0"
#1550
b1101 ~
b1111 n
b10011 V
b10101 N
b11001 F
1"
#1560
0"
#1570
b11010 F
b10110 N
b10100 V
b10000 n
b1110 ~
1"
#1580
0"
#1590
b1111 ~
b10001 n
b10101 V
b10111 N
b11011 F
1"
#1600
0"
#1610
b11100 F
b11000 N
b10110 V
b10010 n
b10000 ~
1"
#1620
0"
#1630
b10001 ~
b10011 n
b10111 V
b11001 N
b11101 F
1"
#1640
0"
#1650
b11110 F
b11010 N
b11000 V
b10100 n
b10010 ~
1"
#1660
0"
#1670
b10011 ~
b10101 n
b11001 V
b11011 N
b11111 F
1"
#1680
0"
#1690
b100000 F
b11100 N
b11010 V
b10110 n
b10100 ~
1"
#1700
0"
#1710
b10101 ~
b10111 n
b11011 V
b11101 N
b100001 F
1"
#1720
0"
#1730
b100010 F
b11110 N
b11100 V
b11000 n
b10110 ~
1"
#1740
0"
#1750
b10111 ~
b11001 n
b11101 V
b11111 N
b100011 F
1"
#1760
0"
#1770
b100100 F
b100000 N
b11110 V
b11010 n
b11000 ~
1"
#1780
0"
#1790
b11001 ~
b11011 n
b11111 V
b100001 N
b100101 F
1"
#1800
0"
#1810
b100110 F
b100010 N
b100000 V
b11100 n
b11010 ~
1"
#1820
0"
#1830
b11011 ~
b11101 n
b100001 V
b100011 N
b100111 F
1"
#1840
0"
#1850
b101000 F
b100100 N
b100010 V
b11110 n
b11100 ~
1"
#1860
0"
#1870
b11101 ~
b11111 n
b100011 V
b100101 N
b101001 F
1"
#1880
0"
#1890
b101010 F
b100110 N
b100100 V
b100000 n
b11110 ~
1"
#1900
0"
#1910
b11111 ~
b100001 n
b100101 V
b100111 N
b101011 F
1"
#1920
0"
#1930
b101100 F
b101000 N
b100110 V
b100010 n
b100000 ~
1"
#1940
0"
#1950
b100001 ~
b100011 n
b100111 V
b101001 N
b101101 F
1"
#1960
0"
#1970
b101110 F
b101010 N
b101000 V
b100100 n
b100010 ~
1"
#1980
0"
#1990
b100011 ~
b100101 n
b101001 V
b101011 N
b101111 F
1"
#2000
0"
#2010
b110000 F
b101100 N
b101010 V
b100110 n
b100100 ~
1"
#2020
0"
#2030
b100101 ~
b100111 n
b101011 V
b101101 N
b110001 F
1"
#2040
0"
#2050
b110010 F
b101110 N
b101100 V
b101000 n
b100110 ~
1"
#2060
0"
#2070
b100111 ~
b101001 n
b101101 V
b101111 N
0I
b1x1xx110 $
b10 E
b0 F
1"
#2080
0"
#2090
b1 F
b110000 N
b101110 V
b101010 n
b101000 ~
1"
#2100
0"
#2110
b101001 ~
b101011 n
b101111 V
b110001 N
b10 F
1"
#2120
0"
#2130
b11 F
b110010 N
b110000 V
b101100 n
b101010 ~
1"
#2140
0"
#2150
b101011 ~
b101101 n
b110001 V
b10 M
b0 N
b100 F
1"
#2160
0"
#2170
b101 F
b1 N
b110010 V
b101110 n
b101100 ~
1"
#2180
0"
#2190
b101101 ~
b101111 n
0Y
b1x1xx010 $
b10 U
b0 V
b10 N
b110 F
1"
#2200
0"
#2210
b111 F
b11 N
b1 V
b110000 n
b101110 ~
1"
#2220
0"
#2230
b101111 ~
b110001 n
b10 V
b100 N
b1000 F
1"
#2240
0"
#2250
b1001 F
b101 N
b11 V
b110010 n
b110000 ~
1"
#2260
0"
#2270
b110001 ~
0q
b1x0xx010 $
b10 m
b0 n
b100 V
b110 N
b1010 F
1"
#2280
0"
#2290
b1011 F
b111 N
b101 V
b1 n
b110010 ~
1"
#2300
0"
#2310
0#"
b0x0xx010 $
b10 }
b0 ~
b10 n
b110 V
b1000 N
b1100 F
1"
#2320
0"
#2330
b1101 F
b1001 N
b111 V
b11 n
b1 ~
1"
#2340
0"
#2350
b10 ~
b100 n
b1000 V
b1010 N
b1110 F
1"
#2360
0"
#2370
b1111 F
b1011 N
b1001 V
b101 n
b11 ~
1"
#2380
0"
#2390
b100 ~
b110 n
b1010 V
b1100 N
b10000 F
1"
#2400
0"
#2410
b10001 F
b1101 N
b1011 V
b111 n
b101 ~
1"
#2420
0"
#2430
b110 ~
b1000 n
b1100 V
b1110 N
b10010 F
1"
#2440
0"
#2450
b10011 F
b1111 N
b1101 V
b1001 n
b111 ~
1"
#2460
0"
#2470
b1000 ~
b1010 n
b1110 V
b10000 N
b10100 F
1"
#2480
0"
#2490
b10101 F
b10001 N
b1111 V
b1011 n
b1001 ~
1"
#2500
0"
#2510
b1010 ~
b1100 n
b10000 V
b10010 N
b10110 F
1"
#2520
0"
#2530
b10111 F
b10011 N
b10001 V
b1101 n
b1011 ~
1"
#2540
0"
#2550
b1100 ~
b1110 n
b10010 V
b10100 N
b11000 F
1"
#2560
0"
#2570
b11001 F
b10101 N
b10011 V
b1111 n
b1101 ~
1"
#2580
0"
#2590
b1110 ~
b10000 n
b10100 V
b10110 N
b11010 F
1"
#2600
0"
#2610
b11011 F
b10111 N
b10101 V
b10001 n
b1111 ~
1"
#2620
0"
#2630
b10000 ~
b10010 n
b10110 V
b11000 N
b11100 F
1"
#2640
0"
#2650
b11101 F
b11001 N
b10111 V
b10011 n
b10001 ~
1"
#2660
0"
#2670
b10010 ~
b10100 n
b11000 V
b11010 N
b11110 F
1"
#2680
0"
#2690
b11111 F
b11011 N
b11001 V
b10101 n
b10011 ~
1"
#2700
0"
#2710
b10100 ~
b10110 n
b11010 V
b11100 N
b100000 F
1"
#2720
0"
#2730
b100001 F
b11101 N
b11011 V
b10111 n
b10101 ~
1"
#2740
0"
#2750
b10110 ~
b11000 n
b11100 V
b11110 N
b100010 F
1"
#2760
0"
#2770
b100011 F
b11111 N
b11101 V
b11001 n
b10111 ~
1"
#2780
0"
#2790
b11000 ~
b11010 n
b11110 V
b100000 N
b100100 F
1"
#2800
0"
#2810
b100101 F
b100001 N
b11111 V
b11011 n
b11001 ~
1"
#2820
0"
#2830
b11010 ~
b11100 n
b100000 V
b100010 N
b100110 F
1"
#2840
0"
#2850
b100111 F
b100011 N
b100001 V
b11101 n
b11011 ~
1"
#2860
0"
#2870
b11100 ~
b11110 n
b100010 V
b100100 N
b101000 F
1"
#2880
0"
#2890
b101001 F
b100101 N
b100011 V
b11111 n
b11101 ~
1"
#2900
0"
#2910
b11110 ~
b100000 n
b100100 V
b100110 N
b101010 F
1"
#2920
0"
#2930
b101011 F
b100111 N
b100101 V
b100001 n
b11111 ~
1"
#2940
0"
#2950
b100000 ~
b100010 n
b100110 V
b101000 N
b101100 F
1"
#2960
0"
#2970
b101101 F
b101001 N
b100111 V
b100011 n
b100001 ~
1"
#2980
0"
#2990
b100010 ~
b100100 n
b101000 V
b101010 N
b101110 F
1"
#3000
0"
#3010
b101111 F
b101011 N
b101001 V
b100101 n
b100011 ~
1"
#3020
0"
#3030
b100100 ~
b100110 n
b101010 V
b101100 N
b110000 F
1"
#3040
0"
#3050
b110001 F
b101101 N
b101011 V
b100111 n
b100101 ~
1"
#3060
0"
#3070
b100110 ~
b101000 n
b101100 V
b101110 N
b110010 F
1"
#3080
0"
#3090
b11 E
b0 F
b101111 N
b101101 V
b101001 n
b100111 ~
1"
#3100
0"
#3110
b101000 ~
b101010 n
b101110 V
b110000 N
b1 F
1"
#3120
0"
#3130
b10 F
b110001 N
b101111 V
b101011 n
b101001 ~
1"
#3140
0"
#3150
b101010 ~
b101100 n
b110000 V
b110010 N
b11 F
1"
#3160
0"
#3170
b100 F
b11 M
b0 N
b110001 V
b101101 n
b101011 ~
1"
#3180
0"
#3190
b101100 ~
b101110 n
b110010 V
b1 N
b101 F
1"
#3200
0"
#3210
b110 F
b10 N
b11 U
b0 V
b101111 n
b101101 ~
1"
#3220
0"
#3230
b101110 ~
b110000 n
b1 V
b11 N
b111 F
1"
#3240
0"
#3250
b1000 F
b100 N
b10 V
b110001 n
b101111 ~
1"
#3260
0"
#3270
b110000 ~
b110010 n
b11 V
b101 N
b1001 F
1"
#3280
0"
#3290
b1010 F
b110 N
b100 V
b11 m
b0 n
b110001 ~
1"
#3300
0"
#3310
b110010 ~
b1 n
b101 V
b111 N
b1011 F
1"
#3320
0"
#3330
b1100 F
b1000 N
b110 V
b10 n
b11 }
b0 ~
1"
#3340
0"
#3350
b1 ~
b11 n
b111 V
b1001 N
b1101 F
1"
#3360
0"
#3370
b1110 F
b1010 N
b1000 V
b100 n
b10 ~
1"
#3380
0"
#3390
b11 ~
b101 n
b1001 V
b1011 N
b1111 F
1"
#3400
0"
#3410
b10000 F
b1100 N
b1010 V
b110 n
b100 ~
1"
#3420
0"
#3430
b101 ~
b111 n
b1011 V
b1101 N
b10001 F
1"
#3440
0"
#3450
b10010 F
b1110 N
b1100 V
b1000 n
b110 ~
1"
#3460
0"
#3470
b111 ~
b1001 n
b1101 V
b1111 N
b10011 F
1"
#3480
0"
#3490
b10100 F
b10000 N
b1110 V
b1010 n
b1000 ~
1"
#3500
0"
#3510
b1001 ~
b1011 n
b1111 V
b10001 N
b10101 F
1"
#3520
0"
#3530
b10110 F
b10010 N
b10000 V
b1100 n
b1010 ~
1"
#3540
0"
#3550
b1011 ~
b1101 n
b10001 V
b10011 N
b10111 F
1"
#3560
0"
#3570
b11000 F
b10100 N
b10010 V
b1110 n
b1100 ~
1"
#3580
0"
#3590
b1101 ~
b1111 n
b10011 V
b10101 N
b11001 F
1"
#3600
0"
#3610
b11010 F
b10110 N
b10100 V
b10000 n
b1110 ~
1"
#3620
0"
#3630
b1111 ~
b10001 n
b10101 V
b10111 N
b11011 F
1"
#3640
0"
#3650
b11100 F
b11000 N
b10110 V
b10010 n
b10000 ~
1"
#3660
0"
#3670
b10001 ~
b10011 n
b10111 V
b11001 N
b11101 F
1"
#3680
0"
#3690
b11110 F
b11010 N
b11000 V
b10100 n
b10010 ~
1"
#3700
0"
#3710
b10011 ~
b10101 n
b11001 V
b11011 N
b11111 F
1"
#3720
0"
#3730
b100000 F
b11100 N
b11010 V
b10110 n
b10100 ~
1"
#3740
0"
#3750
b10101 ~
b10111 n
b11011 V
b11101 N
b100001 F
1"
#3760
0"
#3770
b100010 F
b11110 N
b11100 V
b11000 n
b10110 ~
1"
#3780
0"
#3790
b10111 ~
b11001 n
b11101 V
b11111 N
b100011 F
1"
#3800
0"
#3810
b100100 F
b100000 N
b11110 V
b11010 n
b11000 ~
1"
#3820
0"
#3830
b11001 ~
b11011 n
b11111 V
b100001 N
b100101 F
1"
#3840
0"
#3850
b100110 F
b100010 N
b100000 V
b11100 n
b11010 ~
1"
#3860
0"
#3870
b11011 ~
b11101 n
b100001 V
b100011 N
b100111 F
1"
#3880
0"
#3890
b101000 F
b100100 N
b100010 V
b11110 n
b11100 ~
1"
#3900
0"
#3910
b11101 ~
b11111 n
b100011 V
b100101 N
b101001 F
1"
#3920
0"
#3930
b101010 F
b100110 N
b100100 V
b100000 n
b11110 ~
1"
#3940
0"
#3950
b11111 ~
b100001 n
b100101 V
b100111 N
b101011 F
1"
#3960
0"
#3970
b101100 F
b101000 N
b100110 V
b100010 n
b100000 ~
1"
#3980
0"
#3990
b100001 ~
b100011 n
b100111 V
b101001 N
b101101 F
1"
#4000
0"
#4010
b101110 F
b101010 N
b101000 V
b100100 n
b100010 ~
1"
#4020
0"
#4030
b100011 ~
b100101 n
b101001 V
b101011 N
b101111 F
1"
#4040
0"
#4050
b110000 F
b101100 N
b101010 V
b100110 n
b100100 ~
1"
#4060
0"
#4070
b100101 ~
b100111 n
b101011 V
b101101 N
b110001 F
1"
#4080
0"
#4090
b110010 F
b101110 N
b101100 V
b101000 n
b100110 ~
1"
#4100
0"
#4110
b100111 ~
b101001 n
b101101 V
b101111 N
b100 E
b0 F
1"
#4120
0"
#4130
b1 F
b110000 N
b101110 V
b101010 n
b101000 ~
1"
#4140
0"
#4150
b101001 ~
b101011 n
b101111 V
b110001 N
b10 F
1"
#4160
0"
#4170
b11 F
b110010 N
b110000 V
b101100 n
b101010 ~
1"
#4180
0"
#4190
b101011 ~
b101101 n
b110001 V
0Q
b0x0xx000 $
b100 M
b0 N
b100 F
1"
#4200
0"
#4210
b101 F
b1 N
b110010 V
b101110 n
b101100 ~
1"
#4220
0"
