pwm.v
`timescale 1ms / 1ns

module pwm(out,pos,clk,contusec,contmsec);
	
	input[1:0] pos;
	input clk;
	output reg out;

always @(posedge clk) begin

	if(contmsec == 2) out = 1;
	if(contmsec != 2) out = 0;
	
	case(pos)
		2'b00:begin			//Duty de 1ms con periodo de 20ms
			if(contmsec >= 0 && contmsec <= 1000) out = 1;
			if(contmsec > 1000 && contmsec <= 20000)out = 0;
			end
		2'b01:begin			//Duty de 1.333ms con periodo de 20ms
			if(contmsec >= 0 && contmsec <= 1333) out = 1;
			if(contmsec > 1333 && contmsec <= 20000)out = 0;
			end
		2'b10:begin			//Duty de 1.666ms con periodo de 20ms
			if(contmsec >= 0 && contmsec <= 1666) out = 1;
			if(contmsec > 1666 && contmsec <= 20000)out = 0;
			end
		2'b11:begin			//Duty de 2ms con periodo de 20ms
			if(contmsec >= 0 && contmsec <= 2000) out = 1;
			if(contmsec > 2000 && contmsec <= 20000)out = 0;
			end
		default
			out = 0;
	endcase
end

//Contador de ms

output reg [5:0] contusec = 0;
output reg [14:0] contmsec = 0;

always @(posedge clk) begin
	
	if(contusec == 50) begin
		contusec = 0;
		
		if(contmsec == 20000) begin
			contmsec = 0;
		end else begin
			contmsec = contmsec + 1;
		end
		
	end else begin
		contusec = contusec + 1;
	end
end

endmodule

pwm_TB.v
`timescale 1ns / 1ns

module pwm_TB;
	reg[1:0] pos;
	reg clk;
	wire out;
	
	pwm uut(.out(out), .pos(pos), .clk(clk));
	
	//Clk modulo
	initial         clk <= 0;
	always #10 clk <= ~clk;

	initial begin
		pos = 2'b00; #4800;
		pos = 2'b01; #4800;
		pos = 2'b10; #4800;
		pos = 2'b11; #4800;
	end

	initial begin: TEST_CASE
		$dumpfile("pwm_TB.vcd");
		$dumpvars(-1,uut);
		#(2000000) $finish;
	end

endmodule

simulation/pwm_TB.vcd
$date
	Tue Feb 20 16:50:41 2018
$end
$version
	Icarus Verilog
$end
$timescale
	1ns
$end
$scope module pwm_TB $end
$scope module uut $end
$var wire 1 ! clk $end
$var wire 2 " pos [1:0] $end
$var reg 15 # contmsec [14:0] $end
$var reg 6 $ contusec [5:0] $end
$var reg 1 % out $end
$upscope $end
$upscope $end
$enddefinitions $end
#0
$dumpvars
x%
b0 $
b0 #
b0 "
0!
$end
#10
1%
b1 $
1!
#20
0!
#30
b10 $
1%
1!
#40
0!
#50
1%
b11 $
1!
#60
0!
#70
b100 $
1%
1!
#80
0!
#90
1%
b101 $
1!
#100
0!
#110
b110 $
1%
1!
#120
0!
#130
1%
b111 $
1!
#140
0!
#150
b1000 $
1%
1!
#160
0!
#170
1%
b1001 $
1!
#180
0!
#190
b1010 $
1%
1!
#200
0!
#210
1%
b1011 $
1!
#220
0!
#230
b1100 $
1%
1!
#240
0!
#250
1%
b1101 $
1!
#260
0!
#270
b1110 $
1%
1!
#280
0!
#290
1%
b1111 $
1!
#300
0!
#310
b10000 $
1%
1!
#320
0!
#330
1%
b10001 $
1!
#340
0!
#350
b10010 $
1%
1!
#360
0!
#370
1%
b10011 $
1!
#380
0!
#390
b10100 $
1%
1!
#400
0!
#410
1%
b10101 $
1!
#420
0!
#430
b10110 $
1%
1!
#440
0!
#450
1%
b10111 $
1!
#460
0!
#470
b11000 $
1%
1!
#480
0!
#490
1%
b11001 $
1!
#500
0!
#510
b11010 $
1%
1!
#520
0!
#530
1%
b11011 $
1!
#540
0!
#550
b11100 $
1%
1!
#560
0!
#570
1%
b11101 $
1!
#580
0!
#590
b11110 $
1%
1!
#600
0!
#610
1%
b11111 $
1!
#620
0!
#630
b100000 $
1%
1!
#640
0!
#650
1%
b100001 $
1!
#660
0!
#670
b100010 $
1%
1!
#680
0!
#690
1%
b100011 $
1!
#700
0!
#710
b100100 $
1%
1!
#720
0!
#730
1%
b100101 $
1!
#740
0!
#750
b100110 $
1%
1!
#760
0!
#770
1%
b100111 $
1!
#780
0!
#790
b101000 $
1%
1!
#800
0!
#810
1%
b101001 $
1!
#820
0!
#830
b101010 $
1%
1!
#840
0!
#850
1%
b101011 $
1!
#860
0!
#870
b101100 $
1%
1!
#880
0!
#890
1%
b101101 $
1!
#900
0!
#910
b101110 $
1%
1!
#920
0!
#930
1%
b101111 $
1!
#940
0!
#950
b110000 $
1%
1!
#960
0!
#970
1%
b110001 $
1!
#980
0!
#990
b110010 $
1%
1!
#1000
0!
#1010
1%
b1 #
b0 $
1!
#1020
0!
#1030
b1 $
1%
1!
#1040
0!
#1050
1%
b10 $
1!
#1060
0!
#1070
b11 $
1%
1!
#1080
0!
#1090
1%
b100 $
1!
#1100
0!
#1110
b101 $
1%
1!
#1120
0!
#1130
1%
b110 $
1!
#1140
0!
#1150
b111 $
1%
1!
#1160
0!
#1170
1%
b1000 $
1!
#1180
0!
#1190
b1001 $
1%
1!
#1200
0!
#1210
1%
b1010 $
1!
#1220
0!
#1230
b1011 $
1%
1!
#1240
0!
#1250
1%
b1100 $
1!
#1260
0!
#1270
b1101 $
1%
1!
#1280
0!
#1290
1%
b1110 $
1!
#1300
0!
#1310
b1111 $
1%
1!
#1320
0!
#1330
1%
b10000 $
1!
#1340
0!
#1350
b10001 $
1%
1!
#1360
0!
#1370
1%
b10010 $
1!
#1380
0!
#1390
b10011 $
1%
1!
#1400
0!
#1410
1%
b10100 $
1!
#1420
0!
#1430
b10101 $
1%
1!
#1440
0!
#1450
1%
b10110 $
1!
#1460
0!
#1470
b10111 $
1%
1!
#1480
0!
#1490
1%
b11000 $
1!
#1500
0!
#1510
b11001 $
1%
1!
#1520
0!
#1530
1%
b11010 $
1!
#1540
0!
#1550
b11011 $
1%
1!
#1560
0!
#1570
1%
b11100 $
1!
#1580
0!
#1590
b11101 $
1%
1!
#1600
0!
#1610
1%
b11110 $
1!
#1620
0!
#1630
b11111 $
1%
1!
#1640
0!
#1650
1%
b100000 $
1!
#1660
0!
#1670
b100001 $
1%
1!
#1680
0!
#1690
1%
b100010 $
1!
#1700
0!
#1710
b100011 $
1%
1!
#1720
0!
#1730
1%
b100100 $
1!
#1740
0!
#1750
b100101 $
1%
1!
#1760
0!
#1770
1%
b100110 $
1!
#1780
0!
#1790
b100111 $
1%
1!
#1800
0!
#1810
1%
b101000 $
1!
#1820
0!
#1830
b101001 $
1%
1!
#1840
0!
#1850
1%
b101010 $
1!
#1860
0!
#1870
b101011 $
1%
1!
#1880
0!
#1890
1%
b101100 $
1!
#1900
0!
#1910
b101101 $
1%
1!
#1920
0!
#1930
1%
b101110 $
1!
#1940
0!
#1950
b101111 $
1%
1!
#1960
0!
#1970
1%
b110000 $
1!
#1980
0!
#1990
b110001 $
1%
1!
#2000
0!
#2010
1%
b110010 $
1!
#2020
0!
#2030
b10 #
b0 $
1%
1!
#2040
0!
#2050
b1 $
1!
#2060
0!
#2070
b10 $
1!
#2080
0!
#2090
b11 $
1!
#2100
0!
#2110
b100 $
1!
#2120
0!
#2130
b101 $
1!
#2140
0!
#2150
b110 $
1!
#2160
0!
#2170
b111 $
1!
#2180
0!
#2190
b1000 $
1!
#2200
0!
#2210
b1001 $
1!
#2220
0!
#2230
b1010 $
1!
#2240
0!
#2250
b1011 $
1!
#2260
0!
#2270
b1100 $
1!
#2280
0!
#2290
b1101 $
1!
#2300
0!
#2310
b1110 $
1!
#2320
0!
#2330
b1111 $
1!
#2340
0!
#2350
b10000 $
1!
#2360
0!
#2370
b10001 $
1!
#2380
0!
#2390
b10010 $
1!
#2400
0!
#2410
b10011 $
1!
#2420
0!
#2430
b10100 $
1!
#2440
0!
#2450
b10101 $
1!
#2460
0!
#2470
b10110 $
1!
#2480
0!
#2490
b10111 $
1!
#2500
0!
#2510
b11000 $
1!
#2520
0!
#2530
b11001 $
1!
#2540
0!
#2550
b11010 $
1!
#2560
0!
#2570
b11011 $
1!
#2580
0!
#2590
b11100 $
1!
#2600
0!
#2610
b11101 $
1!
#2620
0!
#2630
b11110 $
1!
#2640
0!
#2650
b11111 $
1!
#2660
0!
#2670
b100000 $
1!
#2680
0!
#2690
b100001 $
1!
#2700
0!
#2710
b100010 $
1!
#2720
0!
#2730
b100011 $
1!
#2740
0!
#2750
b100100 $
1!
#2760
0!
#2770
b100101 $
1!
#2780
0!
#2790
b100110 $
1!
#2800
0!
#2810
b100111 $
1!
#2820
0!
#2830
b101000 $
1!
#2840
0!
#2850
b101001 $
1!
#2860
0!
#2870
b101010 $
1!
#2880
0!
#2890
b101011 $
1!
#2900
0!
#2910
b101100 $
1!
#2920
0!
#2930
b101101 $
1!
#2940
0!
#2950
b101110 $
1!
#2960
0!
#2970
b101111 $
1!
#2980
0!
#2990
b110000 $
1!
#3000
0!
#3010
b110001 $
1!
#3020
0!
#3030
b110010 $
1!
#3040
0!
#3050
1%
b11 #
b0 $
1!
#3060
0!
#3070
b1 $
1%
1!
#3080
0!
#3090
1%
b10 $
1!
#3100
0!
#3110
b11 $
1%
1!
#3120
0!
#3130
1%
b100 $
1!
#3140
0!
#3150
b101 $
1%
1!
#3160
0!
#3170
1%
b110 $
1!
#3180
0!
#3190
b111 $
1%
1!
#3200
0!
#3210
1%
b1000 $
1!
#3220
0!
#3230
b1001 $
1%
1!
#3240
0!
#3250
1%
b1010 $
1!
#3260
0!
#3270
b1011 $
1%
1!
#3280
0!
#3290
1%
b1100 $
1!
#3300
0!
#3310
b1101 $
1%
1!
#3320
0!
#3330
1%
b1110 $
1!
#3340
0!
#3350
b1111 $
1%
1!
#3360
0!
#3370
1%
b10000 $
1!
#3380
0!
#3390
b10001 $
1%
1!
#3400
0!
#3410
1%
b10010 $
1!
#3420
0!
#3430
b10011 $
1%
1!
#3440
0!
#3450
1%
b10100 $
1!
#3460
0!
#3470
b10101 $
1%
1!
#3480
0!
#3490
1%
b10110 $
1!
#3500
0!
#3510
b10111 $
1%
1!
#3520
0!
#3530
1%
b11000 $
1!
#3540
0!
#3550
b11001 $
1%
1!
#3560
0!
#3570
1%
b11010 $
1!
#3580
0!
#3590
b11011 $
1%
1!
#3600
0!
#3610
1%
b11100 $
1!
#3620
0!
#3630
b11101 $
1%
1!
#3640
0!
#3650
1%
b11110 $
1!
#3660
0!
#3670
b11111 $
1%
1!
#3680
0!
#3690
1%
b100000 $
1!
#3700
0!
#3710
b100001 $
1%
1!
#3720
0!
#3730
1%
b100010 $
1!
#3740
0!
#3750
b100011 $
1%
1!
#3760
0!
#3770
1%
b100100 $
1!
#3780
0!
#3790
b100101 $
1%
1!
#3800
0!
#3810
1%
b100110 $
1!
#3820
0!
#3830
b100111 $
1%
1!
#3840
0!
#3850
1%
b101000 $
1!
#3860
0!
#3870
b101001 $
1%
1!
#3880
0!
#3890
1%
b101010 $
1!
#3900
0!
#3910
b101011 $
1%
1!
#3920
0!
#3930
1%
b101100 $
1!
#3940
0!
#3950
b101101 $
1%
1!
#3960
0!
#3970
1%
b101110 $
1!
#3980
0!
#3990
b101111 $
1%
1!
#4000
0!
#4010
1%
b110000 $
1!
#4020
0!
#4030
b110001 $
1%
1!
#4040
0!
#4050
1%
b110010 $
1!
#4060
0!
#4070
b100 #
b0 $
1%
1!
#4080
0!
#4090
1%
b1 $
1!
#4100
0!
#4110
b10 $
1%
1!
#4120
0!
#4130
1%
b11 $
1!
#4140
0!
#4150
b100 $
1%
1!
#4160
0!
#4170
1%
b101 $
1!
#4180
0!
#4190
b110 $
1%
1!
#4200
0!
#4210
1%
b111 $
1!
#4220
0!
#4230
b1000 $
1%
1!
#4240
0!
#4250
1%
b1001 $
1!
#4260
0!
#4270
b1010 $
1%
1!
#4280
0!
#4290
1%
b1011 $
1!
#4300
0!
#4310
b1100 $
1%
1!
#4320
0!
#4330
1%
b1101 $
1!
#4340
0!
#4350
b1110 $
1%
1!
#4360
0!
#4370
1%
b1111 $
1!
#4380
0!
#4390
b10000 $
1%
1!
#4400
0!
#4410
1%
b10001 $
1!
#4420
0!
#4430
b10010 $
1%
1!
#4440
0!
#4450
1%
b10011 $
1!
#4460
0!
#4470
b10100 $
1%
1!
#4480
0!
#4490
1%
b10101 $
1!
#4500
0!
#4510
b10110 $
1%
1!
#4520
0!
#4530
1%
b10111 $
1!
#4540
0!
#4550
b11000 $
1%
1!
#4560
0!
#4570
1%
b11001 $
1!
#4580
0!
#4590
b11010 $
1%
1!
#4600
0!
#4610
1%
b11011 $
1!
#4620
0!
#4630
b11100 $
1%
1!
#4640
0!
#4650
1%
b11101 $
1!
#4660
0!
#4670
b11110 $
1%
1!
#4680
0!
#4690
1%
b11111 $
1!
#4700
0!
#4710
b100000 $
1%
1!
#4720
0!
#4730
1%
b100001 $
1!
#4740
0!
#4750
b100010 $
1%
1!
#4760
0!
#4770
1%
b100011 $
1!
#4780
0!
#4790
b100100 $
1%
1!
#4800
0!
b1 "
#4810
1%
b100101 $
1!
#4820
0!
#4830
b100110 $
1%
1!
#4840
0!
#4850
1%
b100111 $
1!
#4860
0!
#4870
b101000 $
1%
1!
#4880
0!
#4890
1%
b101001 $
1!
#4900
0!
#4910
b101010 $
1%
1!
#4920
0!
#4930
1%
b101011 $
1!
#4940
0!
#4950
b101100 $
1%
1!
#4960
0!
#4970
1%
b101101 $
1!
#4980
0!
#4990
b101110 $
1%
1!
#5000
0!
#5010
1%
b101111 $
1!
#5020
0!
#5030
b110000 $
1%
1!
#5040
0!
#5050
1%
b110001 $
1!
#5060
0!
#5070
b110010 $
1%
1!
#5080
0!
#5090
1%
b101 #
b0 $
1!
#5100
0!
#5110
b1 $
1%
1!
#5120
0!
#5130
1%
b10 $
1!
#5140
0!
#5150
b11 $
1%
1!
#5160
0!
#5170
1%
b100 $
1!
#5180
0!
#5190
b101 $
1%
1!
#5200
0!
#5210
1%
b110 $
1!
#5220
0!
#5230
b111 $
1%
1!
#5240
0!
#5250
1%
b1000 $
1!
#5260
0!
#5270
b1001 $
1%
1!
#5280
0!
#5290
1%
b1010 $
1!
#5300
0!
#5310
b1011 $
1%
1!
#5320
0!
#5330
1%
b1100 $
1!
#5340
0!
#5350
b1101 $
1%
1!
#5360
0!
#5370
1%
b1110 $
1!
#5380
0!
#5390
b1111 $
1%
1!
#5400
0!
#5410
1%
b10000 $
1!
#5420
0!
#5430
b10001 $
1%
1!
#5440
0!
#5450
1%
b10010 $
1!
#5460
0!
#5470
b10011 $
1%
1!
#5480
0!
#5490
1%
b10100 $
1!
#5500
0!
#5510
b10101 $
1%
1!
#5520
0!
#5530
1%
b10110 $
1!
#5540
0!
#5550
b10111 $
1%
1!
#5560
0!
#5570
1%
b11000 $
1!
#5580
0!
#5590
b11001 $
1%
1!
#5600
0!
#5610
1%
b11010 $
1!
#5620
0!
#5630
b11011 $
1%
1!
#5640
0!
#5650
1%
b11100 $
1!
#5660
0!
#5670
b11101 $
1%
1!
#5680
0!
#5690
1%
b11110 $
1!
#5700
0!
#5710
b11111 $
1%
1!
#5720
0!
#5730
1%
b100000 $
1!
#5740
0!
#5750
b100001 $
1%
1!
#5760
0!
#5770
1%
b100010 $
1!
#5780
0!
#5790
b100011 $
1%
1!
#5800
0!
#5810
1%
b100100 $
1!
#5820
0!
#5830
b100101 $
1%
1!
#5840
0!
#5850
1%
b100110 $
1!
#5860
0!
#5870
b100111 $
1%
1!
#5880
0!
#5890
1%
b101000 $
1!
#5900
0!
#5910
b101001 $
1%
1!
#5920
0!
#5930
1%
b101010 $
1!
#5940
0!
#5950
b101011 $
1%
1!
#5960
0!
#5970
1%
b101100 $
1!
#5980
0!
#5990
b101101 $
1%
1!
#6000
0!
#6010
1%
b101110 $
1!
#6020
0!
#6030
b101111 $
1%
1!
#6040
0!
#6050
1%
b110000 $
1!
#6060
0!
#6070
b110001 $
1%
1!
#6080
0!
#6090
1%
b110010 $
1!
#6100
0!
#6110
b110 #
b0 $
1%
1!
#6120
0!
#6130
1%
b1 $
1!
#6140
0!
#6150
b10 $
1%
1!
#6160
0!
#6170
1%
b11 $
1!
#6180
0!
#6190
b100 $
1%
1!
#6200
0!
#6210
1%
b101 $
1!
#6220
0!
#6230
b110 $
1%
1!
#6240
0!
#6250
1%
b111 $
1!
#6260
0!
#6270
b1000 $
1%
1!
#6280
0!
#6290
1%
b1001 $
1!
#6300
0!
#6310
b1010 $
1%
1!
#6320
0!
#6330
1%
b1011 $
1!
#6340
0!
#6350
b1100 $
1%
1!
#6360
0!
#6370
1%
b1101 $
1!
#6380
0!
#6390
b1110 $
1%
1!
#6400
0!
#6410
1%
b1111 $
1!
#6420
0!
#6430
b10000 $
1%
1!
#6440
0!
#6450
1%
b10001 $
1!
#6460
0!
#6470
b10010 $
1%
1!
#6480
0!
#6490
1%
b10011 $
1!
#6500
0!
#6510
b10100 $
1%
1!
#6520
0!
#6530
1%
b10101 $
1!
#6540
0!
#6550
b10110 $
1%
1!
#6560
0!
#6570
1%
b10111 $
1!
#6580
0!
#6590
b11000 $
1%
1!
#6600
0!
#6610
1%
b11001 $
1!
#6620
0!
#6630
b11010 $
1%
1!
#6640
0!
#6650
1%
b11011 $
1!
#6660
0!
#6670
b11100 $
1%
1!
#6680
0!
#6690
1%
b11101 $
1!
#6700
0!
#6710
b11110 $
1%
1!
#6720
0!
#6730
1%
b11111 $
1!
#6740
0!
#6750
b100000 $
1%
1!
#6760
0!
#6770
1%
b100001 $
1!
#6780
0!
#6790
b100010 $
1%
1!
#6800
0!
#6810
1%
b100011 $
1!
#6820
0!
#6830
b100100 $
1%
1!
#6840
0!
#6850
1%
b100101 $
1!
#6860
0!
#6870
b100110 $
1%
1!
#6880
0!
#6890
1%
b100111 $
1!
#6900
0!
#6910
b101000 $
1%
1!
#6920
0!
#6930
1%
b101001 $
1!
#6940
0!
#6950
b101010 $
1%
1!
#6960
0!
#6970
1%
b101011 $
1!
#6980
0!
#6990
b101100 $
1%
1!
#7000
0!
#7010
1%
b101101 $
1!
#7020
0!
#7030
b101110 $
1%
1!
#7040
0!
#7050
1%
b101111 $
1!
#7060
0!
#7070
b110000 $
1%
1!
#7080
0!
#7090
1%
b110001 $
1!
#7100
0!
#7110
b110010 $
1%
1!
#7120
0!
#7130
1%
b111 #
b0 $
1!
#7140
0!
#7150
b1 $
1%
1!
#7160
0!
#7170
1%
b10 $
1!
#7180
0!
#7190
b11 $
1%
1!
#7200
0!
#7210
1%
b100 $
1!
#7220
0!
#7230
b101 $
1%
1!
#7240
0!
#7250
1%
b110 $
1!
#7260
0!
#7270
b111 $
1%
1!
#7280
0!
#7290
1%
b1000 $
1!
#7300
0!
#7310
b1001 $
1%
1!
#7320
0!
#7330
1%
b1010 $
1!
#7340
0!
#7350
b1011 $
1%
1!
#7360
0!
#7370
1%
b1100 $
1!
#7380
0!
#7390
b1101 $
1%
1!
#7400
0!
#7410
1%
b1110 $
1!
#7420
0!
#7430
b1111 $
1%
1!
#7440
0!
#7450
1%
b10000 $
1!
#7460
0!
#7470
b10001 $
1%
1!
#7480
0!
#7490
1%
b10010 $
1!
#7500
0!
#7510
b10011 $
1%
1!
#7520
0!
#7530
1%
b10100 $
1!
#7540
0!
#7550
b10101 $
1%
1!
#7560
0!
#7570
1%
b10110 $
1!
#7580
0!
#7590
b10111 $
1%
1!
#7600
0!
#7610
1%
b11000 $
1!
#7620
0!
#7630
b11001 $
1%
1!
#7640
0!
#7650
1%
b11010 $
1!
#7660
0!
#7670
b11011 $
1%
1!
#7680
0!
#7690
1%
b11100 $
1!
#7700
0!
#7710
b11101 $
1%
1!
#7720
0!
#7730
1%
b11110 $
1!
#7740
0!
#7750
b11111 $
1%
1!
#7760
0!
#7770
1%
b100000 $
1!
#7780
0!
#7790
b100001 $
1%
1!
#7800
0!
#7810
1%
b100010 $
1!
#7820
0!
#7830
b100011 $
1%
1!
#7840
0!
#7850
1%
b100100 $
1!
#7860
0!
#7870
b100101 $
1%
1!
#7880
0!
#7890
1%
b100110 $
1!
#7900
0!
#7910
b100111 $
1%
1!
#7920
0!
#7930
1%
b101000 $
1!
#7940
0!
#7950
b101001 $
1%
1!
#7960
0!
#7970
1%
b101010 $
1!
#7980
0!
#7990
b101011 $
1%
1!
#8000
0!
#8010
1%
b101100 $
1!
#8020
0!
#8030
b101101 $
1%
1!
#8040
0!
#8050
1%
b101110 $
1!
#8060
0!
#8070
b101111 $
1%
1!
#8080
0!
#8090
1%
b110000 $
1!
#8100
0!
#8110
b110001 $
1%
1!
#8120
0!
#8130
1%
b110010 $
1!
#8140
0!
#8150
b1000 #
b0 $
1%
1!
#8160
0!
#8170
1%
b1 $
1!
#8180
0!
#8190
b10 $
1%
1!
#8200
0!
#8210
1%
b11 $
1!
#8220
0!
#8230
b100 $
1%
1!
#8240
0!
#8250
1%
b101 $
1!
#8260
0!
#8270
b110 $
1%
1!
#8280
0!
#8290
1%
b111 $
1!
#8300
0!
#8310
b1000 $
1%
1!
#8320
0!
#8330
1%
b1001 $
1!
#8340
0!
#8350
b1010 $
1%
1!
#8360
0!
#8370
1%
b1011 $
1!
#8380
0!
#8390
b1100 $
1%
1!
#8400
0!
#8410
1%
b1101 $
1!
#8420
0!
#8430
b1110 $
1%
1!
#8440
0!
#8450
1%
b1111 $
1!
#8460
0!
#8470
b10000 $
1%
1!
#8480
0!
#8490
1%
b10001 $
1!
#8500
0!
#8510
b10010 $
1%
1!
#8520
0!
#8530
1%
b10011 $
1!
#8540
0!
#8550
b10100 $
1%
1!
#8560
0!
#8570
1%
b10101 $
1!
#8580
0!
#8590
b10110 $
1%
1!
#8600
0!
#8610
1%
b10111 $
1!
#8620
0!
#8630
b11000 $
1%
1!
#8640
0!
#8650
1%
b11001 $
1!
#8660
0!
#8670
b11010 $
1%
1!
#8680
0!
#8690
1%
b11011 $
1!
#8700
0!
#8710
b11100 $
1%
1!
#8720
0!
#8730
1%
b11101 $
1!
#8740
0!
#8750
b11110 $
1%
1!
#8760
0!
#8770
1%
b11111 $
1!
#8780
0!
#8790
b100000 $
1%
1!
#8800
0!
#8810
1%
b100001 $
1!
#8820
0!
#8830
b100010 $
1%
1!
#8840
0!
#8850
1%
b100011 $
1!
#8860
0!
#8870
b100100 $
1%
1!
#8880
0!
#8890
1%
b100101 $
1!
#8900
0!
#8910
b100110 $
1%
1!
#8920
0!
#8930
1%
b100111 $
1!
#8940
0!
#8950
b101000 $
1%
1!
#8960
0!
#8970
1%
b101001 $
1!
#8980
0!
#8990
b101010 $
1%
1!
#9000
0!
#9010
1%
b101011 $
1!
#9020
0!
#9030
b101100 $
1%
1!
#9040
0!
#9050
1%
b101101 $
1!
#9060
0!
#9070
b101110 $
1%
1!
#9080
0!
#9090
1%
b101111 $
1!
#9100
0!
#9110
b110000 $
1%
1!
#9120
0!
#9130
1%
b110001 $
1!
#9140
0!
#9150
b110010 $
1%
1!
#9160
0!
#9170
1%
b1001 #
b0 $
1!
#9180
0!
#9190
b1 $
1%
1!
#9200
0!
#9210
1%
b10 $
1!
#9220
0!
#9230
b11 $
1%
1!
#9240
0!
#9250
1%
b100 $
1!
#9260
0!
#9270
b101 $
1%
1!
#9280
0!
#9290
1%
b110 $
1!
#9300
0!
#9310
b111 $
1%
1!
#9320
0!
#9330
1%
b1000 $
1!
#9340
0!
#9350
b1001 $
1%
1!
#9360
0!
#9370
1%
b1010 $
1!
#9380
0!
#9390
b1011 $
1%
1!
#9400
0!
#9410
1%
b1100 $
1!
#9420
0!
#9430
b1101 $
1%
1!
#9440
0!
#9450
1%
b1110 $
1!
#9460
0!
#9470
b1111 $
1%
1!
#9480
0!
#9490
1%
b10000 $
1!
#9500
0!
#9510
b10001 $
1%
1!
#9520
0!
#9530
1%
b10010 $
1!
#9540
0!
#9550
b10011 $
1%
1!
#9560
0!
#9570
1%
b10100 $
1!
#9580
0!
#9590
b10101 $
1%
1!
#9600
0!
b10 "
#9610
1%
b10110 $
1!
#9620
0!
#9630
b10111 $
1%
1!
#9640
0!
#9650
1%
b11000 $
1!
#9660
0!
#9670
b11001 $
1%
1!
#9680
0!
#9690
1%
b11010 $
1!
#9700
0!
#9710
b11011 $
1%
1!
#9720
0!
#9730
1%
b11100 $
1!
#9740
0!
#9750
b11101 $
1%
1!
#9760
0!
#9770
1%
b11110 $
1!
#9780
0!
#9790
b11111 $
1%
1!
#9800
0!
#9810
1%
b100000 $
1!
#9820
0!
#9830
b100001 $
1%
1!
#9840
0!
#9850
1%
b100010 $
1!
#9860
0!
#9870
b100011 $
1%
1!
#9880
0!
#9890
1%
b100100 $
1!
#9900
0!
#9910
b100101 $
1%
1!
#9920
0!
#9930
1%
b100110 $
1!
#9940
0!
#9950
b100111 $
1%
1!
#9960
0!
#9970
1%
b101000 $
1!
#9980
0!
#9990
b101001 $
1%
1!
#10000
0!
#10010
1%
b101010 $
1!
#10020
0!
#10030
b101011 $
1%
1!
#10040
0!
#10050
1%
b101100 $
1!
#10060
0!
#10070
b101101 $
1%
1!
#10080
0!
#10090
1%
b101110 $
1!
#10100
0!
#10110
b101111 $
1%
1!
#10120
0!
#10130
1%
b110000 $
1!
#10140
0!
#10150
b110001 $
1%
1!
#10160
0!
#10170
1%
b110010 $
1!
#10180
0!
#10190
b1010 #
b0 $
1%
1!
#10200
0!
#10210
1%
b1 $
1!
#10220
0!
#10230
b10 $
1%
1!
#10240
0!
#10250
1%
b11 $
1!
#10260
0!
#10270
b100 $
1%
1!
#10280
0!
#10290
1%
b101 $
1!
#10300
0!
#10310
b110 $
1%
1!
#10320
0!
#10330
1%
b111 $
1!
#10340
0!
#10350
b1000 $
1%
1!
#10360
0!
#10370
1%
b1001 $
1!
#10380
0!
#10390
b1010 $
1%
1!
#10400
0!
#10410
1%
b1011 $
1!
#10420
0!
#10430
b1100 $
1%
1!
#10440
0!
#10450
1%
b1101 $
1!
#10460
0!
#10470
b1110 $
1%
1!
#10480
0!
#10490
1%
b1111 $
1!
#10500
0!
#10510
b10000 $
1%
1!
#10520
0!
#10530
1%
b10001 $
1!
#10540
0!
#10550
b10010 $
1%
1!
#10560
0!
#10570
1%
b10011 $
1!
#10580
0!
#10590
b10100 $
1%
1!
#10600
0!
#10610
1%
b10101 $
1!
#10620
0!
#10630
b10110 $
1%
1!
#10640
0!
#10650
1%
b10111 $
1!
#10660
0!
#10670
b11000 $
1%
1!
#10680
0!
#10690
1%
b11001 $
1!
#10700
0!
#10710
b11010 $
1%
1!
#10720
0!
#10730
1%
b11011 $
1!
#10740
0!
#10750
b11100 $
1%
1!
#10760
0!
#10770
1%
b11101 $
1!
#10780
0!
#10790
b11110 $
1%
1!
#10800
0!
#10810
1%
b11111 $
1!
#10820
0!
#10830
b100000 $
1%
1!
#10840
0!
#10850
1%
b100001 $
1!
#10860
0!
#10870
b100010 $
1%
1!
#10880
0!
#10890
1%
b100011 $
1!
#10900
0!
#10910
b100100 $
1%
1!
#10920
0!
#10930
1%
b100101 $
1!
#10940
0!
#10950
b100110 $
1%
1!
#10960
0!
#10970
1%
b100111 $
1!
#10980
0!
#10990
b101000 $
1%
1!
#11000
0!
#11010
1%
b101001 $
1!
#11020
0!
#11030
b101010 $
1%
1!
#11040
0!
#11050
1%
b101011 $
1!
#11060
0!
#11070
b101100 $
1%
1!
#11080
0!
#11090
1%
b101101 $
1!
#11100
0!
#11110
b101110 $
1%
1!
#11120
0!
#11130
1%
b101111 $
1!
#11140
0!
#11150
b110000 $
1%
1!
#11160
0!
#11170
1%
b110001 $
1!
#11180
0!
#11190
b110010 $
1%
1!
#11200
0!
#11210
1%
b1011 #
b0 $
1!
#11220
0!
#11230
b1 $
1%
1!
#11240
0!
#11250
1%
b10 $
1!
#11260
0!
#11270
b11 $
1%
1!
#11280
0!
#11290
1%
b100 $
1!
#11300
0!
#11310
b101 $
1%
1!
#11320
0!
#11330
1%
b110 $
1!
#11340
0!
#11350
b111 $
1%
1!
#11360
0!
#11370
1%
b1000 $
1!
#11380
0!
#11390
b1001 $
1%
1!
#11400
0!
#11410
1%
b1010 $
1!
#11420
0!
#11430
b1011 $
1%
1!
#11440
0!
#11450
1%
b1100 $
1!
#11460
0!
#11470
b1101 $
1%
1!
#11480
0!
#11490
1%
b1110 $
1!
#11500
0!
#11510
b1111 $
1%
1!
#11520
0!
#11530
1%
b10000 $
1!
#11540
0!
#11550
b10001 $
1%
1!
#11560
0!
#11570
1%
b10010 $
1!
#11580
0!
#11590
b10011 $
1%
1!
#11600
0!
#11610
1%
b10100 $
1!
#11620
0!
#11630
b10101 $
1%
1!
#11640
0!
#11650
1%
b10110 $
1!
#11660
0!
#11670
b10111 $
1%
1!
#11680
0!
#11690
1%
b11000 $
1!
#11700
0!
#11710
b11001 $
1%
1!
#11720
0!
#11730
1%
b11010 $
1!
#11740
0!
#11750
b11011 $
1%
1!
#11760
0!
#11770
1%
b11100 $
1!
#11780
0!
#11790
b11101 $
1%
1!
#11800
0!
#11810
1%
b11110 $
1!
#11820
0!
#11830
b11111 $
1%
1!
#11840
0!
#11850
1%
b100000 $
1!
#11860
0!
#11870
b100001 $
1%
1!
#11880
0!
#11890
1%
b100010 $
1!
#11900
0!
#11910
b100011 $
1%
1!
#11920
0!
#11930
1%
b100100 $
1!
#11940
0!
#11950
b100101 $
1%
1!
#11960
0!
#11970
1%
b100110 $
1!
#11980
0!
#11990
b100111 $
1%
1!
#12000
0!
#12010
1%
b101000 $
1!
#12020
0!
#12030
b101001 $
1%
1!
#12040
0!
#12050
1%
b101010 $
1!
#12060
0!
#12070
b101011 $
1%
1!
#12080
0!
#12090
1%
b101100 $
1!
#12100
0!
#12110
b101101 $
1%
1!
#12120
0!
#12130
1%
b101110 $
1!
#12140
0!
#12150
b101111 $
1%
1!
#12160
0!
#12170
1%
b110000 $
1!
#12180
0!
#12190
b110001 $
1%
1!
#12200
0!
#12210
1%
b110010 $
1!
#12220
0!
#12230
b1100 #
b0 $
1%
1!
#12240
0!
#12250
1%
b1 $
1!
#12260
0!
#12270
b10 $
1%
1!
