pwm.v
`timescale 1ns / 1ps

module pwm(out,pos,clk);
	
	input[1:0] pos;
	input clk;
	output reg out;

always @(posedge clk) begin
	
	case(pos)
		2'b00:begin			//Duty de 1ns con periodo de 20ns
			out = 1;
			#1;
			out = 0;
			#19;
			end
		2'b01:begin			//Duty de 1.333ns con periodo de 20ns
			out = 1;
			#1.333;
			out = 0;
			#18.667;
			end
		2'b10:begin			//Duty de 1.666ns con periodo de 20ns
			out = 1;
			#1.666;
			out = 0;
			#18.334;
			end
		2'b11:begin			//Duty de 2ns con periodo de 20ns
			out = 1;
			#2;
			out = 0;
			#17;
			end
		default
			out = 0;
	endcase
end

endmodule

pwm_TB.v
`timescale 1ns / 1ps

module pwm_TB;
	reg[1:0] pos;
	reg clk;
	wire out;
	
	pwm uut(.out(out), .pos(pos), .clk(clk));
	
	//Clk modulo
	initial         clk <= 0;
	always #0.5 clk <= ~clk;

	initial begin
		pos = 2'b00; #30;
		pos = 2'b01; #30;
		pos = 2'b10; #30;
		pos = 2'b11; #30;
	end

	initial begin: TEST_CASE
		$dumpfile("pwm_TB.vcd");
		$dumpvars(-1,uut);
		#(200) $finish;
	end

endmodule

simulation/pwm_TB.vcd
$date
	Mon Feb 19 16:42:57 2018
$end
$version
	Icarus Verilog
$end
$timescale
	1ps
$end
$scope module pwm_TB $end
$scope module uut $end
$var wire 1 ! clk $end
$var wire 2 " pos [1:0] $end
$var reg 1 # out $end
$upscope $end
$upscope $end
$enddefinitions $end
#0
$dumpvars
x#
b0 "
0!
$end
#500
1#
1!
#1000
0!
#1500
1!
0#
#2000
0!
#2500
1!
#3000
0!
#3500
1!
#4000
0!
#4500
1!
#5000
0!
#5500
1!
#6000
0!
#6500
1!
#7000
0!
#7500
1!
#8000
0!
#8500
1!
#9000
0!
#9500
1!
#10000
0!
#10500
1!
#11000
0!
#11500
1!
#12000
0!
#12500
1!
#13000
0!
#13500
1!
#14000
0!
#14500
1!
#15000
0!
#15500
1!
#16000
0!
#16500
1!
#17000
0!
#17500
1!
#18000
0!
#18500
1!
#19000
0!
#19500
1!
#20000
0!
#20500
1#
1!
#21000
0!
#21500
1!
0#
#22000
0!
#22500
1!
#23000
0!
#23500
1!
#24000
0!
#24500
1!
#25000
0!
#25500
1!
#26000
0!
#26500
1!
#27000
0!
#27500
1!
#28000
0!
#28500
1!
#29000
0!
#29500
1!
#30000
0!
b1 "
#30500
1!
#31000
0!
#31500
1!
#32000
0!
#32500
1!
#33000
0!
#33500
1!
#34000
0!
#34500
1!
#35000
0!
#35500
1!
#36000
0!
#36500
1!
#37000
0!
#37500
1!
#38000
0!
#38500
1!
#39000
0!
#39500
1!
#40000
0!
#40500
1#
1!
#41000
0!
#41500
1!
#41833
0#
#42000
0!
#42500
1!
#43000
0!
#43500
1!
#44000
0!
#44500
1!
#45000
0!
#45500
1!
#46000
0!
#46500
1!
#47000
0!
#47500
1!
#48000
0!
#48500
1!
#49000
0!
#49500
1!
#50000
0!
#50500
1!
#51000
0!
#51500
1!
#52000
0!
#52500
1!
#53000
0!
#53500
1!
#54000
0!
#54500
1!
#55000
0!
#55500
1!
#56000
0!
#56500
1!
#57000
0!
#57500
1!
#58000
0!
#58500
1!
#59000
0!
#59500
1!
#60000
0!
b10 "
#60500
1#
1!
#61000
0!
#61500
1!
#62000
0!
#62166
0#
#62500
1!
#63000
0!
#63500
1!
#64000
0!
#64500
1!
#65000
0!
#65500
1!
#66000
0!
#66500
1!
#67000
0!
#67500
1!
#68000
0!
#68500
1!
#69000
0!
#69500
1!
#70000
0!
#70500
1!
#71000
0!
#71500
1!
#72000
0!
#72500
1!
#73000
0!
#73500
1!
#74000
0!
#74500
1!
#75000
0!
#75500
1!
#76000
0!
#76500
1!
#77000
0!
#77500
1!
#78000
0!
#78500
1!
#79000
0!
#79500
1!
#80000
0!
#80500
1#
1!
#81000
0!
#81500
1!
#82000
0!
#82166
0#
#82500
1!
#83000
0!
#83500
1!
#84000
0!
#84500
1!
#85000
0!
#85500
1!
#86000
0!
#86500
1!
#87000
0!
#87500
1!
#88000
0!
#88500
1!
#89000
0!
#89500
1!
#90000
0!
b11 "
#90500
1!
#91000
0!
#91500
1!
#92000
0!
#92500
1!
#93000
0!
#93500
1!
#94000
0!
#94500
1!
#95000
0!
#95500
1!
#96000
0!
#96500
1!
#97000
0!
#97500
1!
#98000
0!
#98500
1!
#99000
0!
#99500
1!
#100000
0!
#100500
1#
1!
#101000
0!
#101500
1!
#102000
0!
#102500
1!
0#
#103000
0!
#103500
1!
#104000
0!
#104500
1!
#105000
0!
#105500
1!
#106000
0!
#106500
1!
#107000
0!
#107500
1!
#108000
0!
#108500
1!
#109000
0!
#109500
1!
#110000
0!
#110500
1!
#111000
0!
#111500
1!
#112000
0!
#112500
1!
#113000
0!
#113500
1!
#114000
0!
#114500
1!
#115000
0!
#115500
1!
#116000
0!
#116500
1!
#117000
0!
#117500
1!
#118000
0!
#118500
1!
#119000
0!
#119500
1#
1!
#120000
0!
#120500
1!
#121000
0!
#121500
1!
0#
#122000
0!
#122500
1!
#123000
0!
#123500
1!
#124000
0!
#124500
1!
#125000
0!
#125500
1!
#126000
0!
#126500
1!
#127000
0!
#127500
1!
#128000
0!
#128500
1!
#129000
0!
#129500
1!
#130000
0!
#130500
1!
#131000
0!
#131500
1!
#132000
0!
#132500
1!
#133000
0!
#133500
1!
#134000
0!
#134500
1!
#135000
0!
#135500
1!
#136000
0!
#136500
1!
#137000
0!
#137500
1!
#138000
0!
#138500
1#
1!
#139000
0!
#139500
1!
#140000
0!
#140500
1!
0#
#141000
0!
#141500
1!
#142000
0!
#142500
1!
#143000
0!
#143500
1!
#144000
0!
#144500
1!
#145000
0!
#145500
1!
#146000
0!
#146500
1!
#147000
0!
#147500
1!
#148000
0!
#148500
1!
#149000
0!
#149500
1!
#150000
0!
#150500
1!
#151000
0!
#151500
1!
#152000
0!
#152500
1!
#153000
0!
#153500
1!
#154000
0!
#154500
1!
#155000
0!
#155500
1!
#156000
0!
#156500
1!
#157000
0!
#157500
1#
1!
#158000
0!
#158500
1!
#159000
0!
#159500
1!
0#
#160000
0!
#160500
1!
#161000
0!
#161500
1!
#162000
0!
#162500
1!
#163000
0!
#163500
1!
#164000
0!
#164500
1!
#165000
0!
#165500
1!
#166000
0!
#166500
1!
#167000
0!
#167500
1!
#168000
0!
#168500
1!
#169000
0!
#169500
1!
#170000
0!
#170500
1!
#171000
0!
#171500
1!
#172000
0!
#172500
1!
#173000
0!
#173500
1!
#174000
0!
#174500
1!
#175000
0!
#175500
1!
#176000
0!
#176500
1#
1!
#177000
0!
#177500
1!
#178000
0!
#178500
1!
0#
#179000
0!
#179500
1!
#180000
0!
#180500
1!
#181000
0!
#181500
1!
#182000
0!
#182500
1!
#183000
0!
#183500
1!
#184000
0!
#184500
1!
#185000
0!
#185500
1!
#186000
0!
#186500
1!
#187000
0!
#187500
1!
#188000
0!
#188500
1!
#189000
0!
#189500
1!
#190000
0!
#190500
1!
#191000
0!
#191500
1!
#192000
0!
#192500
1!
#193000
0!
#193500
1!
#194000
0!
#194500
1!
#195000
0!
#195500
1#
1!
#196000
0!
#196500
1!
#197000
0!
#197500
1!
0#
